__init__.py
moneywiz_api/__init__.py
moneywiz_api/database_accessor.py
moneywiz_api/moneywiz_api.py
moneywiz_api/types.py
moneywiz_api/utils.py
moneywiz_api/cli/cli.py
moneywiz_api/cli/helpers.py
moneywiz_api/managers/__init__.py
moneywiz_api/managers/account_manager.py
moneywiz_api/managers/category_manager.py
moneywiz_api/managers/investment_holding_manager.py
moneywiz_api/managers/payee_manager.py
moneywiz_api/managers/record_manager.py
moneywiz_api/managers/tag_manager.py
moneywiz_api/managers/transaction_manager.py
moneywiz_api/model/__init__.py
moneywiz_api/model/account.py
moneywiz_api/model/category.py
moneywiz_api/model/investment_holding.py
moneywiz_api/model/payee.py
moneywiz_api/model/raw_data_handler.py
moneywiz_api/model/record.py
moneywiz_api/model/tag.py
moneywiz_api/model/transaction.py
moneywiz_api-1.0.6.dist-info/licenses/LICENSE
moneywiz_api-1.0.6.dist-info/METADATA
moneywiz_api-1.0.6.dist-info/WHEEL
moneywiz_api-1.0.6.dist-info/entry_points.txt
moneywiz_api-1.0.6.dist-info/top_level.txt
moneywiz_api-1.0.6.dist-info/RECORD
