Metadata-Version: 2.4
Name: moneywiz-api
Version: 1.0.6
Summary: A Python api to access moneywiz sqlite database
Author-email: iLeoDo <iLeoDo@gmail.com>
Project-URL: Homepage, https://github.com/ileodo/moneywiz-api
Project-URL: Bug Tracker, https://github.com/ileodo/moneywiz-api/issues
Classifier: Programming Language :: Python :: 3
Classifier: License :: OSI Approved :: MIT License
Classifier: Operating System :: OS Independent
Requires-Python: >=3.10
License-File: LICENSE
Requires-Dist: pandas
Provides-Extra: dev
Requires-Dist: pytest; extra == "dev"
Requires-Dist: pytest-cov; extra == "dev"
Requires-Dist: ruff; extra == "dev"
Requires-Dist: mypy; extra == "dev"
Requires-Dist: build; extra == "dev"
Requires-Dist: twine; extra == "dev"
Dynamic: license-file
